{
  "userId": 8315231560,
  "displayName": "YZ_ISoloAli",
  "status": "in-game",
  "placeId": 80184918744223,
  "jobId": "01d93e50-0547-48ec-8d17-0bc185d9dac1",
  "join": "roblox://placeId=80184918744223&gameInstanceId=01d93e50-0547-48ec-8d17-0bc185d9dac1",
  "follow": "roblox://followUserId=8315231560",
  "web": "https://www.roblox.com/games/start?placeId=80184918744223&gameInstanceId=01d93e50-0547-48ec-8d17-0bc185d9dac1",
  "location": "[3 HOURS🕛] Button Eternal",
  "updatedAt": 1763833886549
}
